<?xml version="1.0" encoding="windows-1251"?>
<DEVICE NAME_DEVICE="ПС &#34;Северная&#34; 110/10 кВ яч. №5 РУ-10 кВ" IDTYPE_DEVICE="1" UUID="{EFA8A5C8-ACF4-4FB8-8948-3525F2AF8C86}" GMT_SHIFT="0" DAYLIGHT="0" COEF_I="120" COEF_U="100" SERIAL_NUMBER="" RANGE="10000" IMP_UNIT="5000" IDTYPE_COUNTER="">
 <CHANNEL IDTYPE_CHANNEL="1" NAME_TYPE="Активная прямая" DATE_START="28.09.2008" DATE_END="29.09.2008 14:43:59">
  <DATAPACKET Version="2.0">
   <METADATA>
    <FIELDS>
     <FIELD attrname="TIME" fieldtype="dateTime"/>
     <FIELD attrname="PERIOD" fieldtype="i4"/>
     <FIELD attrname="VALUE" fieldtype="r8"/>
     <FIELD attrname="VALUE_UNIT" fieldtype="r8"/>
     <FIELD attrname="VALUE_INDICATION" fieldtype="r8"/>
     <FIELD attrname="FLAG" fieldtype="i2"/>
     <FIELD attrname="WINTER_SUMMER" fieldtype="i2"/>
    </FIELDS>
    <PARAMS/>
   </METADATA>
   <ROWDATA>
    <ROW TIME="20080928T00:30:00000" PERIOD="1800" VALUE="0" VALUE_UNIT="0" VALUE_INDICATION="5.6706" FLAG="0" WINTER_SUMMER="0"/>
    <ROW TIME="20080928T01:00:00000" PERIOD="1800" VALUE="0" VALUE_UNIT="0" VALUE_INDICATION="5.6706" FLAG="0" WINTER_SUMMER="0"/>
    <ROW TIME="20080928T01:30:00000" PERIOD="1800" VALUE="0" VALUE_UNIT="0" VALUE_INDICATION="5.6706" FLAG="0" WINTER_SUMMER="0"/>
    <ROW TIME="20080928T02:00:00000" PERIOD="1800" VALUE="0" VALUE_UNIT="0" VALUE_INDICATION="5.6706" FLAG="0" WINTER_SUMMER="0"/>
    <ROW TIME="20080928T02:30:00000" PERIOD="1800" VALUE="0" VALUE_UNIT="0" VALUE_INDICATION="5.6706" FLAG="0" WINTER_SUMMER="0"/>
    <ROW TIME="20080928T03:00:00000" PERIOD="1800" VALUE="0" VALUE_UNIT="0" VALUE_INDICATION="5.6706" FLAG="0" WINTER_SUMMER="0"/>
    <ROW TIME="20080928T03:30:00000" PERIOD="1800" VALUE="0" VALUE_UNIT="0" VALUE_INDICATION="5.6706" FLAG="0" WINTER_SUMMER="0"/>
    <ROW TIME="20080928T04:00:00000" PERIOD="1800" VALUE="0" VALUE_UNIT="0" VALUE_INDICATION="5.6706" FLAG="0" WINTER_SUMMER="0"/>
    <ROW TIME="20080928T04:30:00000" PERIOD="1800" VALUE="0" VALUE_UNIT="0" VALUE_INDICATION="5.6706" FLAG="0" WINTER_SUMMER="0"/>
    <ROW TIME="20080928T05:00:00000" PERIOD="1800" VALUE="0" VALUE_UNIT="0" VALUE_INDICATION="5.6706" FLAG="0" WINTER_SUMMER="0"/>
    <ROW TIME="20080928T05:30:00000" PERIOD="1800" VALUE="0" VALUE_UNIT="0" VALUE_INDICATION="5.6706" FLAG="0" WINTER_SUMMER="0"/>
    <ROW TIME="20080928T06:00:00000" PERIOD="1800" VALUE="0" VALUE_UNIT="0" VALUE_INDICATION="5.6706" FLAG="0" WINTER_SUMMER="0"/>
    <ROW TIME="20080928T06:30:00000" PERIOD="1800" VALUE="0" VALUE_UNIT="0" VALUE_INDICATION="5.6706" FLAG="0" WINTER_SUMMER="0"/>
    <ROW TIME="20080928T07:00:00000" PERIOD="1800" VALUE="0" VALUE_UNIT="0" VALUE_INDICATION="5.6706" FLAG="0" WINTER_SUMMER="0"/>
    <ROW TIME="20080928T07:30:00000" PERIOD="1800" VALUE="0" VALUE_UNIT="0" VALUE_INDICATION="5.6706" FLAG="0" WINTER_SUMMER="0"/>
    <ROW TIME="20080928T08:00:00000" PERIOD="1800" VALUE="0" VALUE_UNIT="0" VALUE_INDICATION="5.6706" FLAG="0" WINTER_SUMMER="0"/>
    <ROW TIME="20080928T08:30:00000" PERIOD="1800" VALUE="0" VALUE_UNIT="0" VALUE_INDICATION="5.6706" FLAG="0" WINTER_SUMMER="0"/>
    <ROW TIME="20080928T09:00:00000" PERIOD="1800" VALUE="0" VALUE_UNIT="0" VALUE_INDICATION="5.6706" FLAG="0" WINTER_SUMMER="0"/>
    <ROW TIME="20080928T09:30:00000" PERIOD="1800" VALUE="0" VALUE_UNIT="0" VALUE_INDICATION="5.6706" FLAG="0" WINTER_SUMMER="0"/>
    <ROW TIME="20080928T10:00:00000" PERIOD="1800" VALUE="0" VALUE_UNIT="0" VALUE_INDICATION="5.6706" FLAG="0" WINTER_SUMMER="0"/>
    <ROW TIME="20080928T10:30:00000" PERIOD="1800" VALUE="0" VALUE_UNIT="0" VALUE_INDICATION="5.6706" FLAG="0" WINTER_SUMMER="0"/>
    <ROW TIME="20080928T11:00:00000" PERIOD="1800" VALUE="0" VALUE_UNIT="0" VALUE_INDICATION="5.6706" FLAG="0" WINTER_SUMMER="0"/>
    <ROW TIME="20080928T11:30:00000" PERIOD="1800" VALUE="0" VALUE_UNIT="0" VALUE_INDICATION="5.6706" FLAG="0" WINTER_SUMMER="0"/>
    <ROW TIME="20080928T12:00:00000" PERIOD="1800" VALUE="0" VALUE_UNIT="0" VALUE_INDICATION="5.6706" FLAG="0" WINTER_SUMMER="0"/>
    <ROW TIME="20080928T12:30:00000" PERIOD="1800" VALUE="0" VALUE_UNIT="0" VALUE_INDICATION="5.6706" FLAG="0" WINTER_SUMMER="0"/>
    <ROW TIME="20080928T13:00:00000" PERIOD="1800" VALUE="0" VALUE_UNIT="0" VALUE_INDICATION="5.6706" FLAG="0" WINTER_SUMMER="0"/>
    <ROW TIME="20080928T13:30:00000" PERIOD="1800" VALUE="0" VALUE_UNIT="0" VALUE_INDICATION="5.6706" FLAG="0" WINTER_SUMMER="0"/>
    <ROW TIME="20080928T14:00:00000" PERIOD="1800" VALUE="0" VALUE_UNIT="0" VALUE_INDICATION="5.6706" FLAG="0" WINTER_SUMMER="0"/>
    <ROW TIME="20080928T14:30:00000" PERIOD="1800" VALUE="0" VALUE_UNIT="0" VALUE_INDICATION="5.6706" FLAG="0" WINTER_SUMMER="0"/>
    <ROW TIME="20080928T15:00:00000" PERIOD="1800" VALUE="0" VALUE_UNIT="0" VALUE_INDICATION="5.6706" FLAG="0" WINTER_SUMMER="0"/>
    <ROW TIME="20080928T15:30:00000" PERIOD="1800" VALUE="0" VALUE_UNIT="0" VALUE_INDICATION="5.6706" FLAG="0" WINTER_SUMMER="0"/>
    <ROW TIME="20080928T16:00:00000" PERIOD="1800" VALUE="0" VALUE_UNIT="0" VALUE_INDICATION="5.6706" FLAG="0" WINTER_SUMMER="0"/>
    <ROW TIME="20080928T16:30:00000" PERIOD="1800" VALUE="0" VALUE_UNIT="0" VALUE_INDICATION="5.6706" FLAG="0" WINTER_SUMMER="0"/>
    <ROW TIME="20080928T17:00:00000" PERIOD="1800" VALUE="0" VALUE_UNIT="0" VALUE_INDICATION="5.6706" FLAG="0" WINTER_SUMMER="0"/>
    <ROW TIME="20080928T17:30:00000" PERIOD="1800" VALUE="0" VALUE_UNIT="0" VALUE_INDICATION="5.6706" FLAG="0" WINTER_SUMMER="0"/>
    <ROW TIME="20080928T18:00:00000" PERIOD="1800" VALUE="0" VALUE_UNIT="0" VALUE_INDICATION="5.6706" FLAG="0" WINTER_SUMMER="0"/>
    <ROW TIME="20080928T18:30:00000" PERIOD="1800" VALUE="0" VALUE_UNIT="0" VALUE_INDICATION="5.6706" FLAG="0" WINTER_SUMMER="0"/>
    <ROW TIME="20080928T19:00:00000" PERIOD="1800" VALUE="0" VALUE_UNIT="0" VALUE_INDICATION="5.6706" FLAG="0" WINTER_SUMMER="0"/>
    <ROW TIME="20080928T19:30:00000" PERIOD="1800" VALUE="0" VALUE_UNIT="0" VALUE_INDICATION="5.6706" FLAG="0" WINTER_SUMMER="0"/>
    <ROW TIME="20080928T20:00:00000" PERIOD="1800" VALUE="0" VALUE_UNIT="0" VALUE_INDICATION="5.6706" FLAG="0" WINTER_SUMMER="0"/>
    <ROW TIME="20080928T20:30:00000" PERIOD="1800" VALUE="0" VALUE_UNIT="0" VALUE_INDICATION="5.6706" FLAG="0" WINTER_SUMMER="0"/>
    <ROW TIME="20080928T21:00:00000" PERIOD="1800" VALUE="0" VALUE_UNIT="0" VALUE_INDICATION="5.6706" FLAG="0" WINTER_SUMMER="0"/>
    <ROW TIME="20080928T21:30:00000" PERIOD="1800" VALUE="0" VALUE_UNIT="0" VALUE_INDICATION="5.6706" FLAG="0" WINTER_SUMMER="0"/>
    <ROW TIME="20080928T22:00:00000" PERIOD="1800" VALUE="0" VALUE_UNIT="0" VALUE_INDICATION="5.6706" FLAG="0" WINTER_SUMMER="0"/>
    <ROW TIME="20080928T22:30:00000" PERIOD="1800" VALUE="0" VALUE_UNIT="0" VALUE_INDICATION="5.6706" FLAG="0" WINTER_SUMMER="0"/>
    <ROW TIME="20080928T23:00:00000" PERIOD="1800" VALUE="0" VALUE_UNIT="0" VALUE_INDICATION="5.6706" FLAG="0" WINTER_SUMMER="0"/>
    <ROW TIME="20080928T23:30:00000" PERIOD="1800" VALUE="0" VALUE_UNIT="0" VALUE_INDICATION="5.6706" FLAG="0" WINTER_SUMMER="0"/>
    <ROW TIME="20080929" PERIOD="1800" VALUE="0" VALUE_UNIT="0" VALUE_INDICATION="5.6706" FLAG="0" WINTER_SUMMER="0"/>
    <ROW TIME="20080929T00:30:00000" PERIOD="1800" VALUE="0" VALUE_UNIT="0" VALUE_INDICATION="5.6706" FLAG="0" WINTER_SUMMER="0"/>
    <ROW TIME="20080929T01:00:00000" PERIOD="1800" VALUE="0" VALUE_UNIT="0" VALUE_INDICATION="5.6706" FLAG="0" WINTER_SUMMER="0"/>
    <ROW TIME="20080929T01:30:00000" PERIOD="1800" VALUE="0" VALUE_UNIT="0" VALUE_INDICATION="5.6706" FLAG="0" WINTER_SUMMER="0"/>
    <ROW TIME="20080929T02:00:00000" PERIOD="1800" VALUE="0" VALUE_UNIT="0" VALUE_INDICATION="5.6706" FLAG="0" WINTER_SUMMER="0"/>
    <ROW TIME="20080929T02:30:00000" PERIOD="1800" VALUE="0" VALUE_UNIT="0" VALUE_INDICATION="5.6706" FLAG="0" WINTER_SUMMER="0"/>
    <ROW TIME="20080929T03:00:00000" PERIOD="1800" VALUE="0" VALUE_UNIT="0" VALUE_INDICATION="5.6706" FLAG="0" WINTER_SUMMER="0"/>
    <ROW TIME="20080929T03:30:00000" PERIOD="1800" VALUE="0" VALUE_UNIT="0" VALUE_INDICATION="5.6706" FLAG="0" WINTER_SUMMER="0"/>
    <ROW TIME="20080929T04:00:00000" PERIOD="1800" VALUE="0" VALUE_UNIT="0" VALUE_INDICATION="5.6706" FLAG="0" WINTER_SUMMER="0"/>
    <ROW TIME="20080929T04:30:00000" PERIOD="1800" VALUE="0" VALUE_UNIT="0" VALUE_INDICATION="5.6706" FLAG="0" WINTER_SUMMER="0"/>
    <ROW TIME="20080929T05:00:00000" PERIOD="1800" VALUE="0" VALUE_UNIT="0" VALUE_INDICATION="5.6706" FLAG="0" WINTER_SUMMER="0"/>
    <ROW TIME="20080929T05:30:00000" PERIOD="1800" VALUE="0" VALUE_UNIT="0" VALUE_INDICATION="5.6706" FLAG="0" WINTER_SUMMER="0"/>
    <ROW TIME="20080929T06:00:00000" PERIOD="1800" VALUE="0" VALUE_UNIT="0" VALUE_INDICATION="5.6706" FLAG="0" WINTER_SUMMER="0"/>
    <ROW TIME="20080929T06:30:00000" PERIOD="1800" VALUE="0" VALUE_UNIT="0" VALUE_INDICATION="5.6706" FLAG="0" WINTER_SUMMER="0"/>
    <ROW TIME="20080929T07:00:00000" PERIOD="1800" VALUE="0" VALUE_UNIT="0" VALUE_INDICATION="5.6706" FLAG="0" WINTER_SUMMER="0"/>
    <ROW TIME="20080929T07:30:00000" PERIOD="1800" VALUE="0" VALUE_UNIT="0" VALUE_INDICATION="5.6706" FLAG="0" WINTER_SUMMER="0"/>
    <ROW TIME="20080929T08:00:00000" PERIOD="1800" VALUE="0" VALUE_UNIT="0" VALUE_INDICATION="5.6706" FLAG="0" WINTER_SUMMER="0"/>
    <ROW TIME="20080929T08:30:00000" PERIOD="1800" VALUE="0" VALUE_UNIT="0" VALUE_INDICATION="5.6706" FLAG="0" WINTER_SUMMER="0"/>
    <ROW TIME="20080929T09:00:00000" PERIOD="1800" VALUE="0" VALUE_UNIT="0" VALUE_INDICATION="5.6706" FLAG="0" WINTER_SUMMER="0"/>
    <ROW TIME="20080929T09:30:00000" PERIOD="1800" VALUE="0" VALUE_UNIT="0" VALUE_INDICATION="5.6706" FLAG="0" WINTER_SUMMER="0"/>
    <ROW TIME="20080929T10:00:00000" PERIOD="1800" VALUE="0" VALUE_UNIT="0" VALUE_INDICATION="5.6706" FLAG="0" WINTER_SUMMER="0"/>
    <ROW TIME="20080929T10:30:00000" PERIOD="1800" VALUE="0" VALUE_UNIT="0" VALUE_INDICATION="5.6706" FLAG="0" WINTER_SUMMER="0"/>
    <ROW TIME="20080929T11:00:00000" PERIOD="1800" VALUE="0" VALUE_UNIT="0" VALUE_INDICATION="5.6706" FLAG="0" WINTER_SUMMER="0"/>
    <ROW TIME="20080929T11:30:00000" PERIOD="1800" VALUE="0" VALUE_UNIT="0" VALUE_INDICATION="5.6706" FLAG="0" WINTER_SUMMER="0"/>
    <ROW TIME="20080929T12:00:00000" PERIOD="1800" VALUE="0" VALUE_UNIT="0" VALUE_INDICATION="5.6706" FLAG="0" WINTER_SUMMER="0"/>
    <ROW TIME="20080929T12:30:00000" PERIOD="1800" VALUE="0" VALUE_UNIT="0" VALUE_INDICATION="5.6706" FLAG="0" WINTER_SUMMER="0"/>
    <ROW TIME="20080929T13:00:00000" PERIOD="1800" VALUE="0" VALUE_UNIT="0" VALUE_INDICATION="5.6706" FLAG="0" WINTER_SUMMER="0"/>
    <ROW TIME="20080929T13:30:00000" PERIOD="1800" VALUE="0" VALUE_UNIT="0" VALUE_INDICATION="5.6706" FLAG="0" WINTER_SUMMER="0"/>
    <ROW TIME="20080929T14:00:00000" PERIOD="1800" VALUE="0" VALUE_UNIT="0" VALUE_INDICATION="5.6706" FLAG="0" WINTER_SUMMER="0"/>
    <ROW TIME="20080929T14:30:00000" PERIOD="1800" VALUE="0" VALUE_UNIT="0" VALUE_INDICATION="5.6706" FLAG="0" WINTER_SUMMER="0"/>
   </ROWDATA>
  </DATAPACKET>
 </CHANNEL>
 <CHANNEL IDTYPE_CHANNEL="2" NAME_TYPE="Активная обратная" DATE_START="28.09.2008" DATE_END="29.09.2008 14:43:59">
  <DATAPACKET Version="2.0">
   <METADATA>
    <FIELDS>
     <FIELD attrname="TIME" fieldtype="dateTime"/>
     <FIELD attrname="PERIOD" fieldtype="i4"/>
     <FIELD attrname="VALUE" fieldtype="r8"/>
     <FIELD attrname="VALUE_UNIT" fieldtype="r8"/>
     <FIELD attrname="VALUE_INDICATION" fieldtype="r8"/>
     <FIELD attrname="FLAG" fieldtype="i2"/>
     <FIELD attrname="WINTER_SUMMER" fieldtype="i2"/>
    </FIELDS>
    <PARAMS/>
   </METADATA>
   <ROWDATA>
    <ROW TIME="20080928T00:30:00000" PERIOD="1800" VALUE="0" VALUE_UNIT="0" VALUE_INDICATION="9.6698" FLAG="0" WINTER_SUMMER="0"/>
    <ROW TIME="20080928T01:00:00000" PERIOD="1800" VALUE="0" VALUE_UNIT="0" VALUE_INDICATION="9.6698" FLAG="0" WINTER_SUMMER="0"/>
    <ROW TIME="20080928T01:30:00000" PERIOD="1800" VALUE="0" VALUE_UNIT="0" VALUE_INDICATION="9.6698" FLAG="0" WINTER_SUMMER="0"/>
    <ROW TIME="20080928T02:00:00000" PERIOD="1800" VALUE="0" VALUE_UNIT="0" VALUE_INDICATION="9.6698" FLAG="0" WINTER_SUMMER="0"/>
    <ROW TIME="20080928T02:30:00000" PERIOD="1800" VALUE="0" VALUE_UNIT="0" VALUE_INDICATION="9.6698" FLAG="0" WINTER_SUMMER="0"/>
    <ROW TIME="20080928T03:00:00000" PERIOD="1800" VALUE="0" VALUE_UNIT="0" VALUE_INDICATION="9.6698" FLAG="0" WINTER_SUMMER="0"/>
    <ROW TIME="20080928T03:30:00000" PERIOD="1800" VALUE="0" VALUE_UNIT="0" VALUE_INDICATION="9.6698" FLAG="0" WINTER_SUMMER="0"/>
    <ROW TIME="20080928T04:00:00000" PERIOD="1800" VALUE="0" VALUE_UNIT="0" VALUE_INDICATION="9.6698" FLAG="0" WINTER_SUMMER="0"/>
    <ROW TIME="20080928T04:30:00000" PERIOD="1800" VALUE="0" VALUE_UNIT="0" VALUE_INDICATION="9.6698" FLAG="0" WINTER_SUMMER="0"/>
    <ROW TIME="20080928T05:00:00000" PERIOD="1800" VALUE="0" VALUE_UNIT="0" VALUE_INDICATION="9.6698" FLAG="0" WINTER_SUMMER="0"/>
    <ROW TIME="20080928T05:30:00000" PERIOD="1800" VALUE="0" VALUE_UNIT="0" VALUE_INDICATION="9.6698" FLAG="0" WINTER_SUMMER="0"/>
    <ROW TIME="20080928T06:00:00000" PERIOD="1800" VALUE="0" VALUE_UNIT="0" VALUE_INDICATION="9.6698" FLAG="0" WINTER_SUMMER="0"/>
    <ROW TIME="20080928T06:30:00000" PERIOD="1800" VALUE="0" VALUE_UNIT="0" VALUE_INDICATION="9.6698" FLAG="0" WINTER_SUMMER="0"/>
    <ROW TIME="20080928T07:00:00000" PERIOD="1800" VALUE="0" VALUE_UNIT="0" VALUE_INDICATION="9.6698" FLAG="0" WINTER_SUMMER="0"/>
    <ROW TIME="20080928T07:30:00000" PERIOD="1800" VALUE="0" VALUE_UNIT="0" VALUE_INDICATION="9.6698" FLAG="0" WINTER_SUMMER="0"/>
    <ROW TIME="20080928T08:00:00000" PERIOD="1800" VALUE="0" VALUE_UNIT="0" VALUE_INDICATION="9.6698" FLAG="0" WINTER_SUMMER="0"/>
    <ROW TIME="20080928T08:30:00000" PERIOD="1800" VALUE="0" VALUE_UNIT="0" VALUE_INDICATION="9.6698" FLAG="0" WINTER_SUMMER="0"/>
    <ROW TIME="20080928T09:00:00000" PERIOD="1800" VALUE="0" VALUE_UNIT="0" VALUE_INDICATION="9.6698" FLAG="0" WINTER_SUMMER="0"/>
    <ROW TIME="20080928T09:30:00000" PERIOD="1800" VALUE="0" VALUE_UNIT="0" VALUE_INDICATION="9.6698" FLAG="0" WINTER_SUMMER="0"/>
    <ROW TIME="20080928T10:00:00000" PERIOD="1800" VALUE="0" VALUE_UNIT="0" VALUE_INDICATION="9.6698" FLAG="0" WINTER_SUMMER="0"/>
    <ROW TIME="20080928T10:30:00000" PERIOD="1800" VALUE="0" VALUE_UNIT="0" VALUE_INDICATION="9.6698" FLAG="0" WINTER_SUMMER="0"/>
    <ROW TIME="20080928T11:00:00000" PERIOD="1800" VALUE="0" VALUE_UNIT="0" VALUE_INDICATION="9.6698" FLAG="0" WINTER_SUMMER="0"/>
    <ROW TIME="20080928T11:30:00000" PERIOD="1800" VALUE="0" VALUE_UNIT="0" VALUE_INDICATION="9.6698" FLAG="0" WINTER_SUMMER="0"/>
    <ROW TIME="20080928T12:00:00000" PERIOD="1800" VALUE="0" VALUE_UNIT="0" VALUE_INDICATION="9.6698" FLAG="0" WINTER_SUMMER="0"/>
    <ROW TIME="20080928T12:30:00000" PERIOD="1800" VALUE="0" VALUE_UNIT="0" VALUE_INDICATION="9.6698" FLAG="0" WINTER_SUMMER="0"/>
    <ROW TIME="20080928T13:00:00000" PERIOD="1800" VALUE="0" VALUE_UNIT="0" VALUE_INDICATION="9.6698" FLAG="0" WINTER_SUMMER="0"/>
    <ROW TIME="20080928T13:30:00000" PERIOD="1800" VALUE="0" VALUE_UNIT="0" VALUE_INDICATION="9.6698" FLAG="0" WINTER_SUMMER="0"/>
    <ROW TIME="20080928T14:00:00000" PERIOD="1800" VALUE="0" VALUE_UNIT="0" VALUE_INDICATION="9.6698" FLAG="0" WINTER_SUMMER="0"/>
    <ROW TIME="20080928T14:30:00000" PERIOD="1800" VALUE="0" VALUE_UNIT="0" VALUE_INDICATION="9.6698" FLAG="0" WINTER_SUMMER="0"/>
    <ROW TIME="20080928T15:00:00000" PERIOD="1800" VALUE="0" VALUE_UNIT="0" VALUE_INDICATION="9.6698" FLAG="0" WINTER_SUMMER="0"/>
    <ROW TIME="20080928T15:30:00000" PERIOD="1800" VALUE="0" VALUE_UNIT="0" VALUE_INDICATION="9.6698" FLAG="0" WINTER_SUMMER="0"/>
    <ROW TIME="20080928T16:00:00000" PERIOD="1800" VALUE="0" VALUE_UNIT="0" VALUE_INDICATION="9.6698" FLAG="0" WINTER_SUMMER="0"/>
    <ROW TIME="20080928T16:30:00000" PERIOD="1800" VALUE="0" VALUE_UNIT="0" VALUE_INDICATION="9.6698" FLAG="0" WINTER_SUMMER="0"/>
    <ROW TIME="20080928T17:00:00000" PERIOD="1800" VALUE="0" VALUE_UNIT="0" VALUE_INDICATION="9.6698" FLAG="0" WINTER_SUMMER="0"/>
    <ROW TIME="20080928T17:30:00000" PERIOD="1800" VALUE="0" VALUE_UNIT="0" VALUE_INDICATION="9.6698" FLAG="0" WINTER_SUMMER="0"/>
    <ROW TIME="20080928T18:00:00000" PERIOD="1800" VALUE="0" VALUE_UNIT="0" VALUE_INDICATION="9.6698" FLAG="0" WINTER_SUMMER="0"/>
    <ROW TIME="20080928T18:30:00000" PERIOD="1800" VALUE="0" VALUE_UNIT="0" VALUE_INDICATION="9.6698" FLAG="0" WINTER_SUMMER="0"/>
    <ROW TIME="20080928T19:00:00000" PERIOD="1800" VALUE="0" VALUE_UNIT="0" VALUE_INDICATION="9.6698" FLAG="0" WINTER_SUMMER="0"/>
    <ROW TIME="20080928T19:30:00000" PERIOD="1800" VALUE="0" VALUE_UNIT="0" VALUE_INDICATION="9.6698" FLAG="0" WINTER_SUMMER="0"/>
    <ROW TIME="20080928T20:00:00000" PERIOD="1800" VALUE="0" VALUE_UNIT="0" VALUE_INDICATION="9.6698" FLAG="0" WINTER_SUMMER="0"/>
    <ROW TIME="20080928T20:30:00000" PERIOD="1800" VALUE="0" VALUE_UNIT="0" VALUE_INDICATION="9.6698" FLAG="0" WINTER_SUMMER="0"/>
    <ROW TIME="20080928T21:00:00000" PERIOD="1800" VALUE="0" VALUE_UNIT="0" VALUE_INDICATION="9.6698" FLAG="0" WINTER_SUMMER="0"/>
    <ROW TIME="20080928T21:30:00000" PERIOD="1800" VALUE="0" VALUE_UNIT="0" VALUE_INDICATION="9.6698" FLAG="0" WINTER_SUMMER="0"/>
    <ROW TIME="20080928T22:00:00000" PERIOD="1800" VALUE="0" VALUE_UNIT="0" VALUE_INDICATION="9.6698" FLAG="0" WINTER_SUMMER="0"/>
    <ROW TIME="20080928T22:30:00000" PERIOD="1800" VALUE="0" VALUE_UNIT="0" VALUE_INDICATION="9.6698" FLAG="0" WINTER_SUMMER="0"/>
    <ROW TIME="20080928T23:00:00000" PERIOD="1800" VALUE="0" VALUE_UNIT="0" VALUE_INDICATION="9.6698" FLAG="0" WINTER_SUMMER="0"/>
    <ROW TIME="20080928T23:30:00000" PERIOD="1800" VALUE="0" VALUE_UNIT="0" VALUE_INDICATION="9.6698" FLAG="0" WINTER_SUMMER="0"/>
    <ROW TIME="20080929" PERIOD="1800" VALUE="0" VALUE_UNIT="0" VALUE_INDICATION="9.6698" FLAG="0" WINTER_SUMMER="0"/>
    <ROW TIME="20080929T00:30:00000" PERIOD="1800" VALUE="0" VALUE_UNIT="0" VALUE_INDICATION="9.6698" FLAG="0" WINTER_SUMMER="0"/>
    <ROW TIME="20080929T01:00:00000" PERIOD="1800" VALUE="0" VALUE_UNIT="0" VALUE_INDICATION="9.6698" FLAG="0" WINTER_SUMMER="0"/>
    <ROW TIME="20080929T01:30:00000" PERIOD="1800" VALUE="0" VALUE_UNIT="0" VALUE_INDICATION="9.6698" FLAG="0" WINTER_SUMMER="0"/>
    <ROW TIME="20080929T02:00:00000" PERIOD="1800" VALUE="0" VALUE_UNIT="0" VALUE_INDICATION="9.6698" FLAG="0" WINTER_SUMMER="0"/>
    <ROW TIME="20080929T02:30:00000" PERIOD="1800" VALUE="0" VALUE_UNIT="0" VALUE_INDICATION="9.6698" FLAG="0" WINTER_SUMMER="0"/>
    <ROW TIME="20080929T03:00:00000" PERIOD="1800" VALUE="0" VALUE_UNIT="0" VALUE_INDICATION="9.6698" FLAG="0" WINTER_SUMMER="0"/>
    <ROW TIME="20080929T03:30:00000" PERIOD="1800" VALUE="0" VALUE_UNIT="0" VALUE_INDICATION="9.6698" FLAG="0" WINTER_SUMMER="0"/>
    <ROW TIME="20080929T04:00:00000" PERIOD="1800" VALUE="0" VALUE_UNIT="0" VALUE_INDICATION="9.6698" FLAG="0" WINTER_SUMMER="0"/>
    <ROW TIME="20080929T04:30:00000" PERIOD="1800" VALUE="0" VALUE_UNIT="0" VALUE_INDICATION="9.6698" FLAG="0" WINTER_SUMMER="0"/>
    <ROW TIME="20080929T05:00:00000" PERIOD="1800" VALUE="0" VALUE_UNIT="0" VALUE_INDICATION="9.6698" FLAG="0" WINTER_SUMMER="0"/>
    <ROW TIME="20080929T05:30:00000" PERIOD="1800" VALUE="0" VALUE_UNIT="0" VALUE_INDICATION="9.6698" FLAG="0" WINTER_SUMMER="0"/>
    <ROW TIME="20080929T06:00:00000" PERIOD="1800" VALUE="0" VALUE_UNIT="0" VALUE_INDICATION="9.6698" FLAG="0" WINTER_SUMMER="0"/>
    <ROW TIME="20080929T06:30:00000" PERIOD="1800" VALUE="0" VALUE_UNIT="0" VALUE_INDICATION="9.6698" FLAG="0" WINTER_SUMMER="0"/>
    <ROW TIME="20080929T07:00:00000" PERIOD="1800" VALUE="0" VALUE_UNIT="0" VALUE_INDICATION="9.6698" FLAG="0" WINTER_SUMMER="0"/>
    <ROW TIME="20080929T07:30:00000" PERIOD="1800" VALUE="0" VALUE_UNIT="0" VALUE_INDICATION="9.6698" FLAG="0" WINTER_SUMMER="0"/>
    <ROW TIME="20080929T08:00:00000" PERIOD="1800" VALUE="0" VALUE_UNIT="0" VALUE_INDICATION="9.6698" FLAG="0" WINTER_SUMMER="0"/>
    <ROW TIME="20080929T08:30:00000" PERIOD="1800" VALUE="0" VALUE_UNIT="0" VALUE_INDICATION="9.6698" FLAG="0" WINTER_SUMMER="0"/>
    <ROW TIME="20080929T09:00:00000" PERIOD="1800" VALUE="0" VALUE_UNIT="0" VALUE_INDICATION="9.6698" FLAG="0" WINTER_SUMMER="0"/>
    <ROW TIME="20080929T09:30:00000" PERIOD="1800" VALUE="0" VALUE_UNIT="0" VALUE_INDICATION="9.6698" FLAG="0" WINTER_SUMMER="0"/>
    <ROW TIME="20080929T10:00:00000" PERIOD="1800" VALUE="0" VALUE_UNIT="0" VALUE_INDICATION="9.6698" FLAG="0" WINTER_SUMMER="0"/>
    <ROW TIME="20080929T10:30:00000" PERIOD="1800" VALUE="0" VALUE_UNIT="0" VALUE_INDICATION="9.6698" FLAG="0" WINTER_SUMMER="0"/>
    <ROW TIME="20080929T11:00:00000" PERIOD="1800" VALUE="0" VALUE_UNIT="0" VALUE_INDICATION="9.6698" FLAG="0" WINTER_SUMMER="0"/>
    <ROW TIME="20080929T11:30:00000" PERIOD="1800" VALUE="0" VALUE_UNIT="0" VALUE_INDICATION="9.6698" FLAG="0" WINTER_SUMMER="0"/>
    <ROW TIME="20080929T12:00:00000" PERIOD="1800" VALUE="0" VALUE_UNIT="0" VALUE_INDICATION="9.6698" FLAG="0" WINTER_SUMMER="0"/>
    <ROW TIME="20080929T12:30:00000" PERIOD="1800" VALUE="0" VALUE_UNIT="0" VALUE_INDICATION="9.6698" FLAG="0" WINTER_SUMMER="0"/>
    <ROW TIME="20080929T13:00:00000" PERIOD="1800" VALUE="0" VALUE_UNIT="0" VALUE_INDICATION="9.6698" FLAG="0" WINTER_SUMMER="0"/>
    <ROW TIME="20080929T13:30:00000" PERIOD="1800" VALUE="0" VALUE_UNIT="0" VALUE_INDICATION="9.6698" FLAG="0" WINTER_SUMMER="0"/>
    <ROW TIME="20080929T14:00:00000" PERIOD="1800" VALUE="0" VALUE_UNIT="0" VALUE_INDICATION="9.6698" FLAG="0" WINTER_SUMMER="0"/>
    <ROW TIME="20080929T14:30:00000" PERIOD="1800" VALUE="0" VALUE_UNIT="0" VALUE_INDICATION="9.6698" FLAG="0" WINTER_SUMMER="0"/>
   </ROWDATA>
  </DATAPACKET>
 </CHANNEL>
 <CHANNEL IDTYPE_CHANNEL="3" NAME_TYPE="Реактивная прямая" DATE_START="28.09.2008" DATE_END="29.09.2008 14:43:59">
  <DATAPACKET Version="2.0">
   <METADATA>
    <FIELDS>
     <FIELD attrname="TIME" fieldtype="dateTime"/>
     <FIELD attrname="PERIOD" fieldtype="i4"/>
     <FIELD attrname="VALUE" fieldtype="r8"/>
     <FIELD attrname="VALUE_UNIT" fieldtype="r8"/>
     <FIELD attrname="VALUE_INDICATION" fieldtype="r8"/>
     <FIELD attrname="FLAG" fieldtype="i2"/>
     <FIELD attrname="WINTER_SUMMER" fieldtype="i2"/>
    </FIELDS>
    <PARAMS/>
   </METADATA>
   <ROWDATA>
    <ROW TIME="20080928T00:30:00000" PERIOD="1800" VALUE="3" VALUE_UNIT="7.2" VALUE_INDICATION="17.6562" FLAG="0" WINTER_SUMMER="0"/>
    <ROW TIME="20080928T01:00:00000" PERIOD="1800" VALUE="4" VALUE_UNIT="9.6" VALUE_INDICATION="17.657" FLAG="0" WINTER_SUMMER="0"/>
    <ROW TIME="20080928T01:30:00000" PERIOD="1800" VALUE="4" VALUE_UNIT="9.6" VALUE_INDICATION="17.6578" FLAG="0" WINTER_SUMMER="0"/>
    <ROW TIME="20080928T02:00:00000" PERIOD="1800" VALUE="4" VALUE_UNIT="9.6" VALUE_INDICATION="17.6586" FLAG="0" WINTER_SUMMER="0"/>
    <ROW TIME="20080928T02:30:00000" PERIOD="1800" VALUE="4" VALUE_UNIT="9.6" VALUE_INDICATION="17.6594" FLAG="0" WINTER_SUMMER="0"/>
    <ROW TIME="20080928T03:00:00000" PERIOD="1800" VALUE="4" VALUE_UNIT="9.6" VALUE_INDICATION="17.6602" FLAG="0" WINTER_SUMMER="0"/>
    <ROW TIME="20080928T03:30:00000" PERIOD="1800" VALUE="3" VALUE_UNIT="7.2" VALUE_INDICATION="17.6608" FLAG="0" WINTER_SUMMER="0"/>
    <ROW TIME="20080928T04:00:00000" PERIOD="1800" VALUE="4" VALUE_UNIT="9.6" VALUE_INDICATION="17.6616" FLAG="0" WINTER_SUMMER="0"/>
    <ROW TIME="20080928T04:30:00000" PERIOD="1800" VALUE="4" VALUE_UNIT="9.6" VALUE_INDICATION="17.6624" FLAG="0" WINTER_SUMMER="0"/>
    <ROW TIME="20080928T05:00:00000" PERIOD="1800" VALUE="4" VALUE_UNIT="9.6" VALUE_INDICATION="17.6632" FLAG="0" WINTER_SUMMER="0"/>
    <ROW TIME="20080928T05:30:00000" PERIOD="1800" VALUE="3" VALUE_UNIT="7.2" VALUE_INDICATION="17.6638" FLAG="0" WINTER_SUMMER="0"/>
    <ROW TIME="20080928T06:00:00000" PERIOD="1800" VALUE="4" VALUE_UNIT="9.6" VALUE_INDICATION="17.6646" FLAG="0" WINTER_SUMMER="0"/>
    <ROW TIME="20080928T06:30:00000" PERIOD="1800" VALUE="5" VALUE_UNIT="12" VALUE_INDICATION="17.6656" FLAG="0" WINTER_SUMMER="0"/>
    <ROW TIME="20080928T07:00:00000" PERIOD="1800" VALUE="3" VALUE_UNIT="7.2" VALUE_INDICATION="17.6662" FLAG="0" WINTER_SUMMER="0"/>
    <ROW TIME="20080928T07:30:00000" PERIOD="1800" VALUE="3" VALUE_UNIT="7.2" VALUE_INDICATION="17.6668" FLAG="0" WINTER_SUMMER="0"/>
    <ROW TIME="20080928T08:00:00000" PERIOD="1800" VALUE="6" VALUE_UNIT="14.4" VALUE_INDICATION="17.668" FLAG="0" WINTER_SUMMER="0"/>
    <ROW TIME="20080928T08:30:00000" PERIOD="1800" VALUE="3" VALUE_UNIT="7.2" VALUE_INDICATION="17.6686" FLAG="0" WINTER_SUMMER="0"/>
    <ROW TIME="20080928T09:00:00000" PERIOD="1800" VALUE="3" VALUE_UNIT="7.2" VALUE_INDICATION="17.6692" FLAG="0" WINTER_SUMMER="0"/>
    <ROW TIME="20080928T09:30:00000" PERIOD="1800" VALUE="3" VALUE_UNIT="7.2" VALUE_INDICATION="17.6698" FLAG="0" WINTER_SUMMER="0"/>
    <ROW TIME="20080928T10:00:00000" PERIOD="1800" VALUE="5" VALUE_UNIT="12" VALUE_INDICATION="17.6708" FLAG="0" WINTER_SUMMER="0"/>
    <ROW TIME="20080928T10:30:00000" PERIOD="1800" VALUE="4" VALUE_UNIT="9.6" VALUE_INDICATION="17.6716" FLAG="0" WINTER_SUMMER="0"/>
    <ROW TIME="20080928T11:00:00000" PERIOD="1800" VALUE="3" VALUE_UNIT="7.2" VALUE_INDICATION="17.6722" FLAG="0" WINTER_SUMMER="0"/>
    <ROW TIME="20080928T11:30:00000" PERIOD="1800" VALUE="3" VALUE_UNIT="7.2" VALUE_INDICATION="17.6728" FLAG="0" WINTER_SUMMER="0"/>
    <ROW TIME="20080928T12:00:00000" PERIOD="1800" VALUE="5" VALUE_UNIT="12" VALUE_INDICATION="17.6738" FLAG="0" WINTER_SUMMER="0"/>
    <ROW TIME="20080928T12:30:00000" PERIOD="1800" VALUE="4" VALUE_UNIT="9.6" VALUE_INDICATION="17.6746" FLAG="0" WINTER_SUMMER="0"/>
    <ROW TIME="20080928T13:00:00000" PERIOD="1800" VALUE="3" VALUE_UNIT="7.2" VALUE_INDICATION="17.6752" FLAG="0" WINTER_SUMMER="0"/>
    <ROW TIME="20080928T13:30:00000" PERIOD="1800" VALUE="4" VALUE_UNIT="9.6" VALUE_INDICATION="17.676" FLAG="0" WINTER_SUMMER="0"/>
    <ROW TIME="20080928T14:00:00000" PERIOD="1800" VALUE="4" VALUE_UNIT="9.6" VALUE_INDICATION="17.6768" FLAG="0" WINTER_SUMMER="0"/>
    <ROW TIME="20080928T14:30:00000" PERIOD="1800" VALUE="4" VALUE_UNIT="9.6" VALUE_INDICATION="17.6776" FLAG="0" WINTER_SUMMER="0"/>
    <ROW TIME="20080928T15:00:00000" PERIOD="1800" VALUE="3" VALUE_UNIT="7.2" VALUE_INDICATION="17.6782" FLAG="0" WINTER_SUMMER="0"/>
    <ROW TIME="20080928T15:30:00000" PERIOD="1800" VALUE="5" VALUE_UNIT="12" VALUE_INDICATION="17.6792" FLAG="0" WINTER_SUMMER="0"/>
    <ROW TIME="20080928T16:00:00000" PERIOD="1800" VALUE="3" VALUE_UNIT="7.2" VALUE_INDICATION="17.6798" FLAG="0" WINTER_SUMMER="0"/>
    <ROW TIME="20080928T16:30:00000" PERIOD="1800" VALUE="4" VALUE_UNIT="9.6" VALUE_INDICATION="17.6806" FLAG="0" WINTER_SUMMER="0"/>
    <ROW TIME="20080928T17:00:00000" PERIOD="1800" VALUE="4" VALUE_UNIT="9.6" VALUE_INDICATION="17.6814" FLAG="0" WINTER_SUMMER="0"/>
    <ROW TIME="20080928T17:30:00000" PERIOD="1800" VALUE="4" VALUE_UNIT="9.6" VALUE_INDICATION="17.6822" FLAG="0" WINTER_SUMMER="0"/>
    <ROW TIME="20080928T18:00:00000" PERIOD="1800" VALUE="3" VALUE_UNIT="7.2" VALUE_INDICATION="17.6828" FLAG="0" WINTER_SUMMER="0"/>
    <ROW TIME="20080928T18:30:00000" PERIOD="1800" VALUE="4" VALUE_UNIT="9.6" VALUE_INDICATION="17.6836" FLAG="0" WINTER_SUMMER="0"/>
    <ROW TIME="20080928T19:00:00000" PERIOD="1800" VALUE="4" VALUE_UNIT="9.6" VALUE_INDICATION="17.6844" FLAG="0" WINTER_SUMMER="0"/>
    <ROW TIME="20080928T19:30:00000" PERIOD="1800" VALUE="4" VALUE_UNIT="9.6" VALUE_INDICATION="17.6852" FLAG="0" WINTER_SUMMER="0"/>
    <ROW TIME="20080928T20:00:00000" PERIOD="1800" VALUE="3" VALUE_UNIT="7.2" VALUE_INDICATION="17.6858" FLAG="0" WINTER_SUMMER="0"/>
    <ROW TIME="20080928T20:30:00000" PERIOD="1800" VALUE="4" VALUE_UNIT="9.6" VALUE_INDICATION="17.6866" FLAG="0" WINTER_SUMMER="0"/>
    <ROW TIME="20080928T21:00:00000" PERIOD="1800" VALUE="4" VALUE_UNIT="9.6" VALUE_INDICATION="17.6874" FLAG="0" WINTER_SUMMER="0"/>
    <ROW TIME="20080928T21:30:00000" PERIOD="1800" VALUE="4" VALUE_UNIT="9.6" VALUE_INDICATION="17.6882" FLAG="0" WINTER_SUMMER="0"/>
    <ROW TIME="20080928T22:00:00000" PERIOD="1800" VALUE="3" VALUE_UNIT="7.2" VALUE_INDICATION="17.6888" FLAG="0" WINTER_SUMMER="0"/>
    <ROW TIME="20080928T22:30:00000" PERIOD="1800" VALUE="4" VALUE_UNIT="9.6" VALUE_INDICATION="17.6896" FLAG="0" WINTER_SUMMER="0"/>
    <ROW TIME="20080928T23:00:00000" PERIOD="1800" VALUE="3" VALUE_UNIT="7.2" VALUE_INDICATION="17.6902" FLAG="0" WINTER_SUMMER="0"/>
    <ROW TIME="20080928T23:30:00000" PERIOD="1800" VALUE="5" VALUE_UNIT="12" VALUE_INDICATION="17.6912" FLAG="0" WINTER_SUMMER="0"/>
    <ROW TIME="20080929" PERIOD="1800" VALUE="4" VALUE_UNIT="9.6" VALUE_INDICATION="17.692" FLAG="0" WINTER_SUMMER="0"/>
    <ROW TIME="20080929T00:30:00000" PERIOD="1800" VALUE="3" VALUE_UNIT="7.2" VALUE_INDICATION="17.6926" FLAG="0" WINTER_SUMMER="0"/>
    <ROW TIME="20080929T01:00:00000" PERIOD="1800" VALUE="4" VALUE_UNIT="9.6" VALUE_INDICATION="17.6934" FLAG="0" WINTER_SUMMER="0"/>
    <ROW TIME="20080929T01:30:00000" PERIOD="1800" VALUE="4" VALUE_UNIT="9.6" VALUE_INDICATION="17.6942" FLAG="0" WINTER_SUMMER="0"/>
    <ROW TIME="20080929T02:00:00000" PERIOD="1800" VALUE="4" VALUE_UNIT="9.6" VALUE_INDICATION="17.695" FLAG="0" WINTER_SUMMER="0"/>
    <ROW TIME="20080929T02:30:00000" PERIOD="1800" VALUE="3" VALUE_UNIT="7.2" VALUE_INDICATION="17.6956" FLAG="0" WINTER_SUMMER="0"/>
    <ROW TIME="20080929T03:00:00000" PERIOD="1800" VALUE="4" VALUE_UNIT="9.6" VALUE_INDICATION="17.6964" FLAG="0" WINTER_SUMMER="0"/>
    <ROW TIME="20080929T03:30:00000" PERIOD="1800" VALUE="5" VALUE_UNIT="12" VALUE_INDICATION="17.6974" FLAG="0" WINTER_SUMMER="0"/>
    <ROW TIME="20080929T04:00:00000" PERIOD="1800" VALUE="3" VALUE_UNIT="7.2" VALUE_INDICATION="17.698" FLAG="0" WINTER_SUMMER="0"/>
    <ROW TIME="20080929T04:30:00000" PERIOD="1800" VALUE="3" VALUE_UNIT="7.2" VALUE_INDICATION="17.6986" FLAG="0" WINTER_SUMMER="0"/>
    <ROW TIME="20080929T05:00:00000" PERIOD="1800" VALUE="5" VALUE_UNIT="12" VALUE_INDICATION="17.6996" FLAG="0" WINTER_SUMMER="0"/>
    <ROW TIME="20080929T05:30:00000" PERIOD="1800" VALUE="4" VALUE_UNIT="9.6" VALUE_INDICATION="17.7004" FLAG="0" WINTER_SUMMER="0"/>
    <ROW TIME="20080929T06:00:00000" PERIOD="1800" VALUE="3" VALUE_UNIT="7.2" VALUE_INDICATION="17.701" FLAG="0" WINTER_SUMMER="0"/>
    <ROW TIME="20080929T06:30:00000" PERIOD="1800" VALUE="3" VALUE_UNIT="7.2" VALUE_INDICATION="17.7016" FLAG="0" WINTER_SUMMER="0"/>
    <ROW TIME="20080929T07:00:00000" PERIOD="1800" VALUE="5" VALUE_UNIT="12" VALUE_INDICATION="17.7026" FLAG="0" WINTER_SUMMER="0"/>
    <ROW TIME="20080929T07:30:00000" PERIOD="1800" VALUE="3" VALUE_UNIT="7.2" VALUE_INDICATION="17.7032" FLAG="0" WINTER_SUMMER="0"/>
    <ROW TIME="20080929T08:00:00000" PERIOD="1800" VALUE="4" VALUE_UNIT="9.6" VALUE_INDICATION="17.704" FLAG="0" WINTER_SUMMER="0"/>
    <ROW TIME="20080929T08:30:00000" PERIOD="1800" VALUE="3" VALUE_UNIT="7.2" VALUE_INDICATION="17.7046" FLAG="0" WINTER_SUMMER="0"/>
    <ROW TIME="20080929T09:00:00000" PERIOD="1800" VALUE="5" VALUE_UNIT="12" VALUE_INDICATION="17.7056" FLAG="0" WINTER_SUMMER="0"/>
    <ROW TIME="20080929T09:30:00000" PERIOD="1800" VALUE="3" VALUE_UNIT="7.2" VALUE_INDICATION="17.7062" FLAG="0" WINTER_SUMMER="0"/>
    <ROW TIME="20080929T10:00:00000" PERIOD="1800" VALUE="3" VALUE_UNIT="7.2" VALUE_INDICATION="17.7068" FLAG="0" WINTER_SUMMER="0"/>
    <ROW TIME="20080929T10:30:00000" PERIOD="1800" VALUE="3" VALUE_UNIT="7.2" VALUE_INDICATION="17.7074" FLAG="0" WINTER_SUMMER="0"/>
    <ROW TIME="20080929T11:00:00000" PERIOD="1800" VALUE="4" VALUE_UNIT="9.6" VALUE_INDICATION="17.7082" FLAG="0" WINTER_SUMMER="0"/>
    <ROW TIME="20080929T11:30:00000" PERIOD="1800" VALUE="5" VALUE_UNIT="12" VALUE_INDICATION="17.7092" FLAG="0" WINTER_SUMMER="0"/>
    <ROW TIME="20080929T12:00:00000" PERIOD="1800" VALUE="3" VALUE_UNIT="7.2" VALUE_INDICATION="17.7098" FLAG="0" WINTER_SUMMER="0"/>
    <ROW TIME="20080929T12:30:00000" PERIOD="1800" VALUE="3" VALUE_UNIT="7.2" VALUE_INDICATION="17.7104" FLAG="0" WINTER_SUMMER="0"/>
    <ROW TIME="20080929T13:00:00000" PERIOD="1800" VALUE="3" VALUE_UNIT="7.2" VALUE_INDICATION="17.711" FLAG="0" WINTER_SUMMER="0"/>
    <ROW TIME="20080929T13:30:00000" PERIOD="1800" VALUE="5" VALUE_UNIT="12" VALUE_INDICATION="17.712" FLAG="0" WINTER_SUMMER="0"/>
    <ROW TIME="20080929T14:00:00000" PERIOD="1800" VALUE="4" VALUE_UNIT="9.6" VALUE_INDICATION="17.7128" FLAG="0" WINTER_SUMMER="0"/>
    <ROW TIME="20080929T14:30:00000" PERIOD="1800" VALUE="3" VALUE_UNIT="7.2" VALUE_INDICATION="17.7134" FLAG="0" WINTER_SUMMER="0"/>
   </ROWDATA>
  </DATAPACKET>
 </CHANNEL>
 <CHANNEL IDTYPE_CHANNEL="4" NAME_TYPE="Реактивная обратная" DATE_START="28.09.2008" DATE_END="29.09.2008 14:43:59">
  <DATAPACKET Version="2.0">
   <METADATA>
    <FIELDS>
     <FIELD attrname="TIME" fieldtype="dateTime"/>
     <FIELD attrname="PERIOD" fieldtype="i4"/>
     <FIELD attrname="VALUE" fieldtype="r8"/>
     <FIELD attrname="VALUE_UNIT" fieldtype="r8"/>
     <FIELD attrname="VALUE_INDICATION" fieldtype="r8"/>
     <FIELD attrname="FLAG" fieldtype="i2"/>
     <FIELD attrname="WINTER_SUMMER" fieldtype="i2"/>
    </FIELDS>
    <PARAMS/>
   </METADATA>
   <ROWDATA>
    <ROW TIME="20080928T00:30:00000" PERIOD="1800" VALUE="0" VALUE_UNIT="0" VALUE_INDICATION="4.5654" FLAG="0" WINTER_SUMMER="0"/>
    <ROW TIME="20080928T01:00:00000" PERIOD="1800" VALUE="0" VALUE_UNIT="0" VALUE_INDICATION="4.5654" FLAG="0" WINTER_SUMMER="0"/>
    <ROW TIME="20080928T01:30:00000" PERIOD="1800" VALUE="0" VALUE_UNIT="0" VALUE_INDICATION="4.5654" FLAG="0" WINTER_SUMMER="0"/>
    <ROW TIME="20080928T02:00:00000" PERIOD="1800" VALUE="0" VALUE_UNIT="0" VALUE_INDICATION="4.5654" FLAG="0" WINTER_SUMMER="0"/>
    <ROW TIME="20080928T02:30:00000" PERIOD="1800" VALUE="0" VALUE_UNIT="0" VALUE_INDICATION="4.5654" FLAG="0" WINTER_SUMMER="0"/>
    <ROW TIME="20080928T03:00:00000" PERIOD="1800" VALUE="0" VALUE_UNIT="0" VALUE_INDICATION="4.5654" FLAG="0" WINTER_SUMMER="0"/>
    <ROW TIME="20080928T03:30:00000" PERIOD="1800" VALUE="0" VALUE_UNIT="0" VALUE_INDICATION="4.5654" FLAG="0" WINTER_SUMMER="0"/>
    <ROW TIME="20080928T04:00:00000" PERIOD="1800" VALUE="0" VALUE_UNIT="0" VALUE_INDICATION="4.5654" FLAG="0" WINTER_SUMMER="0"/>
    <ROW TIME="20080928T04:30:00000" PERIOD="1800" VALUE="0" VALUE_UNIT="0" VALUE_INDICATION="4.5654" FLAG="0" WINTER_SUMMER="0"/>
    <ROW TIME="20080928T05:00:00000" PERIOD="1800" VALUE="0" VALUE_UNIT="0" VALUE_INDICATION="4.5654" FLAG="0" WINTER_SUMMER="0"/>
    <ROW TIME="20080928T05:30:00000" PERIOD="1800" VALUE="0" VALUE_UNIT="0" VALUE_INDICATION="4.5654" FLAG="0" WINTER_SUMMER="0"/>
    <ROW TIME="20080928T06:00:00000" PERIOD="1800" VALUE="0" VALUE_UNIT="0" VALUE_INDICATION="4.5654" FLAG="0" WINTER_SUMMER="0"/>
    <ROW TIME="20080928T06:30:00000" PERIOD="1800" VALUE="0" VALUE_UNIT="0" VALUE_INDICATION="4.5654" FLAG="0" WINTER_SUMMER="0"/>
    <ROW TIME="20080928T07:00:00000" PERIOD="1800" VALUE="0" VALUE_UNIT="0" VALUE_INDICATION="4.5654" FLAG="0" WINTER_SUMMER="0"/>
    <ROW TIME="20080928T07:30:00000" PERIOD="1800" VALUE="0" VALUE_UNIT="0" VALUE_INDICATION="4.5654" FLAG="0" WINTER_SUMMER="0"/>
    <ROW TIME="20080928T08:00:00000" PERIOD="1800" VALUE="0" VALUE_UNIT="0" VALUE_INDICATION="4.5654" FLAG="0" WINTER_SUMMER="0"/>
    <ROW TIME="20080928T08:30:00000" PERIOD="1800" VALUE="0" VALUE_UNIT="0" VALUE_INDICATION="4.5654" FLAG="0" WINTER_SUMMER="0"/>
    <ROW TIME="20080928T09:00:00000" PERIOD="1800" VALUE="0" VALUE_UNIT="0" VALUE_INDICATION="4.5654" FLAG="0" WINTER_SUMMER="0"/>
    <ROW TIME="20080928T09:30:00000" PERIOD="1800" VALUE="0" VALUE_UNIT="0" VALUE_INDICATION="4.5654" FLAG="0" WINTER_SUMMER="0"/>
    <ROW TIME="20080928T10:00:00000" PERIOD="1800" VALUE="0" VALUE_UNIT="0" VALUE_INDICATION="4.5654" FLAG="0" WINTER_SUMMER="0"/>
    <ROW TIME="20080928T10:30:00000" PERIOD="1800" VALUE="0" VALUE_UNIT="0" VALUE_INDICATION="4.5654" FLAG="0" WINTER_SUMMER="0"/>
    <ROW TIME="20080928T11:00:00000" PERIOD="1800" VALUE="0" VALUE_UNIT="0" VALUE_INDICATION="4.5654" FLAG="0" WINTER_SUMMER="0"/>
    <ROW TIME="20080928T11:30:00000" PERIOD="1800" VALUE="0" VALUE_UNIT="0" VALUE_INDICATION="4.5654" FLAG="0" WINTER_SUMMER="0"/>
    <ROW TIME="20080928T12:00:00000" PERIOD="1800" VALUE="0" VALUE_UNIT="0" VALUE_INDICATION="4.5654" FLAG="0" WINTER_SUMMER="0"/>
    <ROW TIME="20080928T12:30:00000" PERIOD="1800" VALUE="0" VALUE_UNIT="0" VALUE_INDICATION="4.5654" FLAG="0" WINTER_SUMMER="0"/>
    <ROW TIME="20080928T13:00:00000" PERIOD="1800" VALUE="0" VALUE_UNIT="0" VALUE_INDICATION="4.5654" FLAG="0" WINTER_SUMMER="0"/>
    <ROW TIME="20080928T13:30:00000" PERIOD="1800" VALUE="0" VALUE_UNIT="0" VALUE_INDICATION="4.5654" FLAG="0" WINTER_SUMMER="0"/>
    <ROW TIME="20080928T14:00:00000" PERIOD="1800" VALUE="0" VALUE_UNIT="0" VALUE_INDICATION="4.5654" FLAG="0" WINTER_SUMMER="0"/>
    <ROW TIME="20080928T14:30:00000" PERIOD="1800" VALUE="0" VALUE_UNIT="0" VALUE_INDICATION="4.5654" FLAG="0" WINTER_SUMMER="0"/>
    <ROW TIME="20080928T15:00:00000" PERIOD="1800" VALUE="0" VALUE_UNIT="0" VALUE_INDICATION="4.5654" FLAG="0" WINTER_SUMMER="0"/>
    <ROW TIME="20080928T15:30:00000" PERIOD="1800" VALUE="0" VALUE_UNIT="0" VALUE_INDICATION="4.5654" FLAG="0" WINTER_SUMMER="0"/>
    <ROW TIME="20080928T16:00:00000" PERIOD="1800" VALUE="0" VALUE_UNIT="0" VALUE_INDICATION="4.5654" FLAG="0" WINTER_SUMMER="0"/>
    <ROW TIME="20080928T16:30:00000" PERIOD="1800" VALUE="0" VALUE_UNIT="0" VALUE_INDICATION="4.5654" FLAG="0" WINTER_SUMMER="0"/>
    <ROW TIME="20080928T17:00:00000" PERIOD="1800" VALUE="0" VALUE_UNIT="0" VALUE_INDICATION="4.5654" FLAG="0" WINTER_SUMMER="0"/>
    <ROW TIME="20080928T17:30:00000" PERIOD="1800" VALUE="0" VALUE_UNIT="0" VALUE_INDICATION="4.5654" FLAG="0" WINTER_SUMMER="0"/>
    <ROW TIME="20080928T18:00:00000" PERIOD="1800" VALUE="0" VALUE_UNIT="0" VALUE_INDICATION="4.5654" FLAG="0" WINTER_SUMMER="0"/>
    <ROW TIME="20080928T18:30:00000" PERIOD="1800" VALUE="0" VALUE_UNIT="0" VALUE_INDICATION="4.5654" FLAG="0" WINTER_SUMMER="0"/>
    <ROW TIME="20080928T19:00:00000" PERIOD="1800" VALUE="0" VALUE_UNIT="0" VALUE_INDICATION="4.5654" FLAG="0" WINTER_SUMMER="0"/>
    <ROW TIME="20080928T19:30:00000" PERIOD="1800" VALUE="0" VALUE_UNIT="0" VALUE_INDICATION="4.5654" FLAG="0" WINTER_SUMMER="0"/>
    <ROW TIME="20080928T20:00:00000" PERIOD="1800" VALUE="0" VALUE_UNIT="0" VALUE_INDICATION="4.5654" FLAG="0" WINTER_SUMMER="0"/>
    <ROW TIME="20080928T20:30:00000" PERIOD="1800" VALUE="0" VALUE_UNIT="0" VALUE_INDICATION="4.5654" FLAG="0" WINTER_SUMMER="0"/>
    <ROW TIME="20080928T21:00:00000" PERIOD="1800" VALUE="0" VALUE_UNIT="0" VALUE_INDICATION="4.5654" FLAG="0" WINTER_SUMMER="0"/>
    <ROW TIME="20080928T21:30:00000" PERIOD="1800" VALUE="0" VALUE_UNIT="0" VALUE_INDICATION="4.5654" FLAG="0" WINTER_SUMMER="0"/>
    <ROW TIME="20080928T22:00:00000" PERIOD="1800" VALUE="0" VALUE_UNIT="0" VALUE_INDICATION="4.5654" FLAG="0" WINTER_SUMMER="0"/>
    <ROW TIME="20080928T22:30:00000" PERIOD="1800" VALUE="0" VALUE_UNIT="0" VALUE_INDICATION="4.5654" FLAG="0" WINTER_SUMMER="0"/>
    <ROW TIME="20080928T23:00:00000" PERIOD="1800" VALUE="0" VALUE_UNIT="0" VALUE_INDICATION="4.5654" FLAG="0" WINTER_SUMMER="0"/>
    <ROW TIME="20080928T23:30:00000" PERIOD="1800" VALUE="0" VALUE_UNIT="0" VALUE_INDICATION="4.5654" FLAG="0" WINTER_SUMMER="0"/>
    <ROW TIME="20080929" PERIOD="1800" VALUE="0" VALUE_UNIT="0" VALUE_INDICATION="4.5654" FLAG="0" WINTER_SUMMER="0"/>
    <ROW TIME="20080929T00:30:00000" PERIOD="1800" VALUE="0" VALUE_UNIT="0" VALUE_INDICATION="4.5654" FLAG="0" WINTER_SUMMER="0"/>
    <ROW TIME="20080929T01:00:00000" PERIOD="1800" VALUE="0" VALUE_UNIT="0" VALUE_INDICATION="4.5654" FLAG="0" WINTER_SUMMER="0"/>
    <ROW TIME="20080929T01:30:00000" PERIOD="1800" VALUE="0" VALUE_UNIT="0" VALUE_INDICATION="4.5654" FLAG="0" WINTER_SUMMER="0"/>
    <ROW TIME="20080929T02:00:00000" PERIOD="1800" VALUE="0" VALUE_UNIT="0" VALUE_INDICATION="4.5654" FLAG="0" WINTER_SUMMER="0"/>
    <ROW TIME="20080929T02:30:00000" PERIOD="1800" VALUE="0" VALUE_UNIT="0" VALUE_INDICATION="4.5654" FLAG="0" WINTER_SUMMER="0"/>
    <ROW TIME="20080929T03:00:00000" PERIOD="1800" VALUE="0" VALUE_UNIT="0" VALUE_INDICATION="4.5654" FLAG="0" WINTER_SUMMER="0"/>
    <ROW TIME="20080929T03:30:00000" PERIOD="1800" VALUE="0" VALUE_UNIT="0" VALUE_INDICATION="4.5654" FLAG="0" WINTER_SUMMER="0"/>
    <ROW TIME="20080929T04:00:00000" PERIOD="1800" VALUE="0" VALUE_UNIT="0" VALUE_INDICATION="4.5654" FLAG="0" WINTER_SUMMER="0"/>
    <ROW TIME="20080929T04:30:00000" PERIOD="1800" VALUE="0" VALUE_UNIT="0" VALUE_INDICATION="4.5654" FLAG="0" WINTER_SUMMER="0"/>
    <ROW TIME="20080929T05:00:00000" PERIOD="1800" VALUE="0" VALUE_UNIT="0" VALUE_INDICATION="4.5654" FLAG="0" WINTER_SUMMER="0"/>
    <ROW TIME="20080929T05:30:00000" PERIOD="1800" VALUE="0" VALUE_UNIT="0" VALUE_INDICATION="4.5654" FLAG="0" WINTER_SUMMER="0"/>
    <ROW TIME="20080929T06:00:00000" PERIOD="1800" VALUE="0" VALUE_UNIT="0" VALUE_INDICATION="4.5654" FLAG="0" WINTER_SUMMER="0"/>
    <ROW TIME="20080929T06:30:00000" PERIOD="1800" VALUE="0" VALUE_UNIT="0" VALUE_INDICATION="4.5654" FLAG="0" WINTER_SUMMER="0"/>
    <ROW TIME="20080929T07:00:00000" PERIOD="1800" VALUE="0" VALUE_UNIT="0" VALUE_INDICATION="4.5654" FLAG="0" WINTER_SUMMER="0"/>
    <ROW TIME="20080929T07:30:00000" PERIOD="1800" VALUE="0" VALUE_UNIT="0" VALUE_INDICATION="4.5654" FLAG="0" WINTER_SUMMER="0"/>
    <ROW TIME="20080929T08:00:00000" PERIOD="1800" VALUE="0" VALUE_UNIT="0" VALUE_INDICATION="4.5654" FLAG="0" WINTER_SUMMER="0"/>
    <ROW TIME="20080929T08:30:00000" PERIOD="1800" VALUE="0" VALUE_UNIT="0" VALUE_INDICATION="4.5654" FLAG="0" WINTER_SUMMER="0"/>
    <ROW TIME="20080929T09:00:00000" PERIOD="1800" VALUE="0" VALUE_UNIT="0" VALUE_INDICATION="4.5654" FLAG="0" WINTER_SUMMER="0"/>
    <ROW TIME="20080929T09:30:00000" PERIOD="1800" VALUE="0" VALUE_UNIT="0" VALUE_INDICATION="4.5654" FLAG="0" WINTER_SUMMER="0"/>
    <ROW TIME="20080929T10:00:00000" PERIOD="1800" VALUE="0" VALUE_UNIT="0" VALUE_INDICATION="4.5654" FLAG="0" WINTER_SUMMER="0"/>
    <ROW TIME="20080929T10:30:00000" PERIOD="1800" VALUE="0" VALUE_UNIT="0" VALUE_INDICATION="4.5654" FLAG="0" WINTER_SUMMER="0"/>
    <ROW TIME="20080929T11:00:00000" PERIOD="1800" VALUE="0" VALUE_UNIT="0" VALUE_INDICATION="4.5654" FLAG="0" WINTER_SUMMER="0"/>
    <ROW TIME="20080929T11:30:00000" PERIOD="1800" VALUE="0" VALUE_UNIT="0" VALUE_INDICATION="4.5654" FLAG="0" WINTER_SUMMER="0"/>
    <ROW TIME="20080929T12:00:00000" PERIOD="1800" VALUE="0" VALUE_UNIT="0" VALUE_INDICATION="4.5654" FLAG="0" WINTER_SUMMER="0"/>
    <ROW TIME="20080929T12:30:00000" PERIOD="1800" VALUE="0" VALUE_UNIT="0" VALUE_INDICATION="4.5654" FLAG="0" WINTER_SUMMER="0"/>
    <ROW TIME="20080929T13:00:00000" PERIOD="1800" VALUE="0" VALUE_UNIT="0" VALUE_INDICATION="4.5654" FLAG="0" WINTER_SUMMER="0"/>
    <ROW TIME="20080929T13:30:00000" PERIOD="1800" VALUE="0" VALUE_UNIT="0" VALUE_INDICATION="4.5654" FLAG="0" WINTER_SUMMER="0"/>
    <ROW TIME="20080929T14:00:00000" PERIOD="1800" VALUE="0" VALUE_UNIT="0" VALUE_INDICATION="4.5654" FLAG="0" WINTER_SUMMER="0"/>
    <ROW TIME="20080929T14:30:00000" PERIOD="1800" VALUE="0" VALUE_UNIT="0" VALUE_INDICATION="4.5654" FLAG="0" WINTER_SUMMER="0"/>
   </ROWDATA>
  </DATAPACKET>
 </CHANNEL>
</DEVICE>
